tahoe_sites/__init__.py
tahoe_sites/admin.py
tahoe_sites/api.py
tahoe_sites/apps.py
tahoe_sites/backends.py
tahoe_sites/helpers.py
tahoe_sites/models.py
tahoe_sites/permissions.py
tahoe_sites/urls.py
tahoe_sites/views.py
tahoe_sites/zd_helpers.py
tahoe_sites/migrations/0001_initial.py
tahoe_sites/migrations/0002_auto_20220117_0354.py
tahoe_sites/migrations/0003_auto_20220223_1333.py
tahoe_sites/migrations/__init__.py
tahoe_sites/settings/__init__.py
tahoe_sites/settings/common_production.py
tahoe_sites/tests/__init__.py
tahoe_sites/tests/fatories.py
tahoe_sites/tests/test_admin.py
tahoe_sites/tests/test_api.py
tahoe_sites/tests/test_apps.py
tahoe_sites/tests/test_backends.py
tahoe_sites/tests/test_models.py
tahoe_sites/tests/test_permissions.py
tahoe_sites/tests/test_views.py
tahoe_sites/tests/test_zd_helpers.py
tahoe_sites/tests/utils.py
tahoe_sites-1.3.2.dist-info/LICENSE
tahoe_sites-1.3.2.dist-info/METADATA
tahoe_sites-1.3.2.dist-info/WHEEL
tahoe_sites-1.3.2.dist-info/entry_points.txt
tahoe_sites-1.3.2.dist-info/top_level.txt
tahoe_sites-1.3.2.dist-info/RECORD
