Metadata-Version: 2.1
Name: tahoe-sites
Version: 1.3.2
Summary: Site and organization multi-tenancy management for Appsembler Tahoe
Home-page: https://github.com/appsembler/tahoe-sites
Author: Appsembler
Classifier: Framework :: Django
Classifier: Framework :: Django :: 2.2
Classifier: License :: OSI Approved :: MIT License
Classifier: Operating System :: OS Independent
Classifier: Programming Language :: Python
Classifier: Programming Language :: Python :: 3
Classifier: Programming Language :: Python :: 3.5
Classifier: Programming Language :: Python :: 3.8
Requires-Python: >=3.5
License-File: LICENSE
